{"@context":"https://schema.org/","@type":"WebSite","author":{"@type":"Person","name":"Klaus-Ingo Projektemacher"},"hasPart":[{"@context":"https://schema.org/","@id":"https://plastikwarenfabrik.projektemacher.org/post/","@type":"Blog","author":{"@type":"Person","name":"Klaus-Ingo Projektemacher"},"blogPost":[{"@id":"https://plastikwarenfabrik.projektemacher.org/post/acronym-generator/","@type":"BlogPosting","author":{"@type":"Person","name":"Klaus-Ingo Projektemacher"},"dateModified":"2026-05-04","datePublished":"2026-05-04","headline":"Abkürzungsgenerator","inLanguage":"de","name":"Abkürzungsgenerator","url":"https://plastikwarenfabrik.projektemacher.org/post/acronym-generator/"},{"@id":"https://plastikwarenfabrik.projektemacher.org/post/above-the-roofs-of-prague/","@type":"BlogPosting","author":{"@type":"Person","name":"Klaus-Ingo Projektemacher"},"dateModified":"2026-04-11","datePublished":"2026-04-11","headline":"Über den Dächern von Prag","inLanguage":"de","name":"Über den Dächern von Prag","url":"https://plastikwarenfabrik.projektemacher.org/post/above-the-roofs-of-prague/"},{"@id":"https://plastikwarenfabrik.projektemacher.org/post/neo-macintosch/","@type":"BlogPosting","author":{"@type":"Person","name":"Klaus-Ingo Projektemacher"},"dateModified":"2026-04-02","datePublished":"2026-04-01","headline":"Neo MacIntosch","inLanguage":"de","name":"Neo MacIntosch","url":"https://plastikwarenfabrik.projektemacher.org/post/neo-macintosch/"},{"@id":"https://plastikwarenfabrik.projektemacher.org/post/prague/","@type":"BlogPosting","author":{"@type":"Person","name":"Klaus-Ingo Projektemacher"},"dateModified":"2026-03-29","datePublished":"2026-03-24","headline":"Die Prager Helden","inLanguage":"de","name":"Die Prager Helden","url":"https://plastikwarenfabrik.projektemacher.org/post/prague/"},{"@id":"https://plastikwarenfabrik.projektemacher.org/post/ric/","@type":"BlogPosting","author":{"@type":"Person","name":"Klaus-Ingo Projektemacher"},"dateModified":"2026-03-30","datePublished":"2025-11-20","headline":"Gemini macht Ric","inLanguage":"de","name":"Gemini macht Ric","url":"https://plastikwarenfabrik.projektemacher.org/post/ric/"},{"@id":"https://plastikwarenfabrik.projektemacher.org/post/first/","@type":"BlogPosting","author":{"@type":"Person","name":"Klaus-Ingo Projektemacher"},"dateModified":"2026-03-29","datePublished":"2024-01-01","headline":"Willkommen auf dem Information Superhighway!","inLanguage":"de","name":"Willkommen auf dem Information Superhighway!","url":"https://plastikwarenfabrik.projektemacher.org/post/first/"}],"mainEntityOfPage":"https://plastikwarenfabrik.projektemacher.org/post/","name":"Klaus-Ingo's Plastikwarenfabrik - Beiträge"}],"name":"Klaus-Ingo's Plastikwarenfabrik","url":"https://plastikwarenfabrik.projektemacher.org/"}